pyliveofcode/__init__.py
pyliveofcode-0.0.7.dist-info/LICENSE
pyliveofcode-0.0.7.dist-info/METADATA
pyliveofcode-0.0.7.dist-info/WHEEL
pyliveofcode-0.0.7.dist-info/top_level.txt
pyliveofcode-0.0.7.dist-info/RECORD
