Metadata-Version: 2.1
Name: pyliveofcode
Version: 0.0.7
Summary: hi my package do many thing and made by liveofcode
Author: liveofcode
Author-email: liveallgamegamer@gmail.com
Keywords: arithmetic,math,mathematics,python tutorial,avi upadhyay
Classifier: Development Status :: 1 - Planning
Classifier: Intended Audience :: Developers
Classifier: Programming Language :: Python :: 3
Classifier: Operating System :: Unix
Classifier: Operating System :: MacOS :: MacOS X
Classifier: Operating System :: Microsoft :: Windows
License-File: LICENSE
Requires-Dist: pyttsx3
Requires-Dist: SpeechRecognition
Requires-Dist: googletrans
Requires-Dist: nltk
Requires-Dist: scikit-learn
Requires-Dist: playsound
